teleasy/__init__.py
teleasy-1.1.0.dist-info/LICENSE
teleasy-1.1.0.dist-info/METADATA
teleasy-1.1.0.dist-info/WHEEL
teleasy-1.1.0.dist-info/top_level.txt
teleasy-1.1.0.dist-info/RECORD
